mpilot/__init__.py
mpilot/arguments.py
mpilot/cli/__init__.py
mpilot/cli/mpilot.py
mpilot/commands.py
mpilot/exceptions.py
mpilot/libraries/__init__.py
mpilot/libraries/eems/__init__.py
mpilot/libraries/eems/basic.py
mpilot/libraries/eems/csv/__init__.py
mpilot/libraries/eems/csv/io.py
mpilot/libraries/eems/exceptions.py
mpilot/libraries/eems/fuzzy.py
mpilot/libraries/eems/mixins.py
mpilot/libraries/eems/netcdf/__init__.py
mpilot/libraries/eems/netcdf/exceptions.py
mpilot/libraries/eems/netcdf/io.py
mpilot/params.py
mpilot/parser/__init__.py
mpilot/parser/parser.py
mpilot/parser/parsetab.py
mpilot/program.py
mpilot/utils.py
mpilot-1.3.2.dist-info/METADATA
mpilot-1.3.2.dist-info/WHEEL
mpilot-1.3.2.dist-info/entry_points.txt
mpilot-1.3.2.dist-info/licenses/LICENSE
mpilot-1.3.2.dist-info/RECORD
