Metadata-Version: 2.4
Name: mpilot
Version: 1.3.2
Summary: MPilot is a plugin-based, environmental modeling framework
License: MIT
License-File: LICENSE
Author: Conservation Biology Institute
Requires-Python: >=3.11
Classifier: Development Status :: 5 - Production/Stable
Classifier: License :: OSI Approved :: MIT License
Classifier: Programming Language :: Python :: 3
Classifier: Programming Language :: Python :: 3.11
Classifier: Programming Language :: Python :: 3.12
Classifier: Programming Language :: Python :: 3.13
Classifier: Programming Language :: Python :: 3.14
Classifier: Programming Language :: Python :: 3 :: Only
Classifier: Programming Language :: Python :: 3.10
Classifier: Programming Language :: Python :: 3.9
Provides-Extra: netcdf
Requires-Dist: cftime (>=1.6.4,<2.0.0) ; extra == "netcdf"
Requires-Dist: click (>=8.0.4,<9.0.0)
Requires-Dist: netCDF4 (>=1.7.2,<2.0.0) ; (python_version >= "3.11") and (extra == "netcdf")
Requires-Dist: numpy (>=2.3.5,<3.0.0)
Requires-Dist: ply (>=3.11,<4.0)
Requires-Dist: six
Project-URL: Homepage, https://consbio.github.io/mpilot/
Project-URL: Repository, https://github.com/consbio/mpilot
